Metadata-Version: 1.0
Name: qjam
Version: 0.1.0
Summary: UGE qsub command wrapper
Home-page: UNKNOWN
Author: riku.okajima
Author-email: riku.okajima@gmail.com
License: MIT
Platform: UNKNOWN
